ecpro/__init__.py
ecpro/html_slot_config.py
ecpro/image.py
ecpro/img_crop.py
ecpro-0.0.9.dist-info/LICENSE
ecpro-0.0.9.dist-info/METADATA
ecpro-0.0.9.dist-info/WHEEL
ecpro-0.0.9.dist-info/top_level.txt
ecpro-0.0.9.dist-info/RECORD
