Metadata-Version: 2.1
Name: ecpro
Version: 0.0.9
Summary: ecpro image crop utils 新增下颚裁剪点
Home-page: http://git.chaomy.com/libo/ecpro-utils.git
Author: libo
Author-email: 6878595@qq.com
License: UNKNOWN
Project-URL: Bug Tracker, https://github.com/pypa/sampleproject/issues
Platform: UNKNOWN
Classifier: Programming Language :: Python :: 3
Classifier: License :: OSI Approved :: MIT License
Classifier: Operating System :: OS Independent
Requires-Python: >=3.6
